smart_news_organizer/__init__.py
smart_news_organizer/about.py
smart_news_organizer/desktop.py
smart_news_organizer/program.py
smart_news_organizer/icons/logo.png
smart_news_organizer/modules/__init__.py
smart_news_organizer/modules/consult.py
smart_news_organizer/modules/data.py
smart_news_organizer/modules/dates.py
smart_news_organizer/modules/feed.py
smart_news_organizer/modules/files.py
smart_news_organizer/modules/images.py
smart_news_organizer/modules/wabout.py
smart_news_organizer/modules/wmessage.py
smart_news_organizer-0.1.5.dist-info/licenses/LICENSE
smart_news_organizer-0.1.5.dist-info/METADATA
smart_news_organizer-0.1.5.dist-info/WHEEL
smart_news_organizer-0.1.5.dist-info/entry_points.txt
smart_news_organizer-0.1.5.dist-info/top_level.txt
smart_news_organizer-0.1.5.dist-info/RECORD
